odoo/addons/purchase_representative/README.rst
odoo/addons/purchase_representative/__init__.py
odoo/addons/purchase_representative/__manifest__.py
odoo/addons/purchase_representative/i18n/it.po
odoo/addons/purchase_representative/i18n/purchase_representative.pot
odoo/addons/purchase_representative/models/__init__.py
odoo/addons/purchase_representative/models/stock_rule.py
odoo/addons/purchase_representative/readme/CONTRIBUTORS.rst
odoo/addons/purchase_representative/readme/DESCRIPTION.rst
odoo/addons/purchase_representative/readme/USAGE.rst
odoo/addons/purchase_representative/static/description/icon.png
odoo/addons/purchase_representative/static/description/index.html
odoo14_addon_purchase_representative-14.0.1.0.1.dev6.dist-info/METADATA
odoo14_addon_purchase_representative-14.0.1.0.1.dev6.dist-info/WHEEL
odoo14_addon_purchase_representative-14.0.1.0.1.dev6.dist-info/top_level.txt
odoo14_addon_purchase_representative-14.0.1.0.1.dev6.dist-info/RECORD
